vector_chat/__init__.py
vector_chat/__main__.py
vector_chat/cli/__init__.py
vector_chat/cli/chat.py
vector_chat/cli/embed.py
vector_chat/clients.py
vector_chat/config.py
vector_chat/services/__init__.py
vector_chat/services/chunker.py
vector_chat/services/qdrant_service.py
vector_chat-0.1.0.dist-info/LICENSE
vector_chat-0.1.0.dist-info/METADATA
vector_chat-0.1.0.dist-info/WHEEL
vector_chat-0.1.0.dist-info/entry_points.txt
vector_chat-0.1.0.dist-info/RECORD
