Metadata-Version: 2.3
Name: vector-chat
Version: 0.1.0
Summary: A Python toolkit for text embedding with OpenAI and Qdrant, semantic search, and AI-powered chat
Author: Josue Gutierrez
Author-email: josue.ggh@gmail.com
Requires-Python: >=3.8,<4.0
Classifier: Programming Language :: Python :: 3
Classifier: Programming Language :: Python :: 3.8
Classifier: Programming Language :: Python :: 3.9
Classifier: Programming Language :: Python :: 3.10
Classifier: Programming Language :: Python :: 3.11
Classifier: Programming Language :: Python :: 3.12
Classifier: Programming Language :: Python :: 3.13
Requires-Dist: nltk (>=3.8.1,<4.0.0)
Requires-Dist: numpy (>=1.20.0,<2.0.0)
Requires-Dist: openai (>=1.0.0,<2.0.0)
Requires-Dist: python-dotenv (>=1.0.0,<2.0.0)
Requires-Dist: qdrant-client (>=1.6.0,<2.0.0)
Requires-Dist: requests (>=2.31.0,<3.0.0)
